giit/__init__.py
giit/__main__.py
giit/build.py
giit/cache.py
giit/check_output.py
giit/compat.py
giit/config.py
giit/config_reader.py
giit/copy_directory.py
giit/factory.py
giit/fileinfo.py
giit/filelist.py
giit/giit_json.py
giit/git.py
giit/git_repository.py
giit/git_url.py
giit/git_url_parser.py
giit/logs.py
giit/name_to_path_adapter.py
giit/prompt.py
giit/push_command.py
giit/push_config.py
giit/python_command.py
giit/python_environment.py
giit/run_error.py
giit/run_result.py
giit/tasks.py
giit/variables_reader.py
giit/virtualenv.py
giit-8.0.0.dist-info/METADATA
giit-8.0.0.dist-info/WHEEL
giit-8.0.0.dist-info/entry_points.txt
giit-8.0.0.dist-info/top_level.txt
giit-8.0.0.dist-info/RECORD
